pickora/__init__.py
pickora/__main__.py
pickora/compiler.py
pickora/helper.py
pickora-1.0.1.dist-info/LICENSE
pickora-1.0.1.dist-info/METADATA
pickora-1.0.1.dist-info/WHEEL
pickora-1.0.1.dist-info/entry_points.txt
pickora-1.0.1.dist-info/top_level.txt
pickora-1.0.1.dist-info/RECORD
