Metadata-Version: 2.1
Name: pickora
Version: 1.0.1
Summary: A toy compiler that can convert Python scripts into pickle bytecode.
Home-page: https://github.com/splitline/Pickora
Author: splitline
Author-email: tbsthitw@gmail.com
License: UNKNOWN
Platform: UNKNOWN
Classifier: Programming Language :: Python :: 3
Classifier: License :: OSI Approved :: MIT License
Classifier: Operating System :: OS Independent
Requires-Python: >=3.8
License-File: LICENSE
